src/file_utils.py
src/unit_test_agent.py
unittest_gpt-0.1.3.dist-info/LICENSE
unittest_gpt-0.1.3.dist-info/METADATA
unittest_gpt-0.1.3.dist-info/WHEEL
unittest_gpt-0.1.3.dist-info/RECORD
