Metadata-Version: 2.1
Name: unittest-gpt
Version: 0.1.3
Summary: Auto generate unit test using PyTest and Gpt
License: MIT
Author: Akshay Lingamaneni
Requires-Python: >=3.11,<4.0
Classifier: License :: OSI Approved :: MIT License
Classifier: Programming Language :: Python :: 3
Classifier: Programming Language :: Python :: 3.11
Requires-Dist: autopep8 (>=2.0.2,<3.0.0)
Requires-Dist: langchain (>=0.0.199,<0.0.200)
Requires-Dist: openai (>=0.27.8,<0.28.0)
Requires-Dist: pytest (>=7.3.2,<8.0.0)
Requires-Dist: python-dotenv (>=1.0.0,<2.0.0)
